{
  "url": "https://www.reddit.com/r/bangladesh/comments/v2w7aj/%E0%A6%AC%E0%A6%B8_%E0%A6%93_%E0%A6%AE%E0%A7%9F_%E0%A6%AC%E0%A6%A8%E0%A6%A7%E0%A6%AC/",
  "hash": "94dd8582c0eb831a53cde2f683288b46",
  "scraped_at": "2025-12-10T03:10:34.321998",
  "title": "বাসা ও মেয়ে বান্ধবি",
  "description": "আমি যদি আমার নিজের বাসায় আমার মেয়ে বান্ধবীকে নিয়ে আসি এবং তাতে পাশের বাসা বা এলাকার কারো কোন অসুবিধা তৈরি না করি এতে কি আমাকে কারো কোন বাধা দেয়ার বা কিছু বলার (আইনত)এখতিয়ার আছে?",
  "votes": "2",
  "comments": [
    {
      "text": "Basically a Shitpost",
      "votes": "10",
      "replies": [
        {
          "text": "Not really, dude wanted to know if he can use his apartment as Liton’s flat. And if his lawyer neighbor can say anything based on public indecency",
          "votes": "5",
          "replies": []
        }
      ]
    },
    {
      "text": "Your post has been automatically put into the moderation queue for review, due to not meeting one (or more) of the subreddit rules. You can message the moderators and share the link to your post (mandatory) if you do not receive a response within a day or two.\nRule(s): Your account should have at least 5 karma points in order to submit a post.\nI am a bot, and this action was performed automatically. Please contact the moderators of this subreddit if you have any questions or concerns.",
      "votes": "1",
      "replies": []
    },
    {
      "text": "No",
      "votes": "1",
      "replies": []
    },
    {
      "text": "না",
      "votes": "1",
      "replies": []
    },
    {
      "text": "section 290 pc",
      "votes": "1",
      "replies": []
    }
  ],
  "id": 244
}