{
  "url": "https://www.reddit.com/r/bangladesh/comments/1ogjcib/like_in_us_bangladeshs_republican_party_also_gets/",
  "hash": "d710d5390620657d79fcfa8c5c193611",
  "scraped_at": "2025-12-08T17:44:47.893867",
  "title": "Like in US, Bangladesh's Republican Party also gets 'elephant' symbol",
  "description": null,
  "votes": "37",
  "comments": [
    {
      "text": "",
      "votes": "1",
      "replies": []
    },
    {
      "text": "Bangladesh Republican Party funded by an American company owned by former democrats!!!!!!",
      "votes": "24",
      "replies": []
    },
    {
      "text": "Never even heard of them :v",
      "votes": "3",
      "replies": []
    },
    {
      "text": "Baler republican party ke hatir bal markay vote din",
      "votes": "6",
      "replies": [
        {
          "text": "Gali dise 😱\nDOWNVOTE DOWNVOTE 😠",
          "votes": "8",
          "replies": []
        }
      ]
    },
    {
      "text": "Just one out of the hundreds and thousands of political parties created since the July uprising.",
      "votes": "-2",
      "replies": []
    },
    {
      "text": "https://www.tbsnews.net/bangladesh/politics/us-bangladeshs-republican-party-also-gets-elephant-symbol-1269701",
      "votes": "1",
      "replies": []
    },
    {
      "text": "Waiting for the donkey. You know democratic party!! Right!",
      "votes": "1",
      "replies": []
    },
    {
      "text": "Another win for the unemployed",
      "votes": "1",
      "replies": []
    }
  ],
  "id": 177
}