{
  "url": "https://www.reddit.com/r/bangladesh/comments/1kvli21/anyone_going_to_us_this_fall_for_university/",
  "hash": "cde64a64cc9e24f7ad7db1962703680d",
  "scraped_at": "2025-12-10T01:58:31.410005",
  "title": "Anyone going to US this fall for University?",
  "description": "Hey everyone, I’m going to UCF this fall 2025. And I want to know if any of my fellow Bengalis from this group are going there as well. I’m going to Orlando Florida, and I would love to be friends if any one of you are going or already went to US 🙏🏻",
  "votes": "6",
  "comments": [
    {
      "text": "Did you get the visa?",
      "votes": "3",
      "replies": [
        {
          "text": "Yea, I went to give my interview on 22nd May and got approved",
          "votes": "3",
          "replies": [
            {
              "text": "Wait until you get the visa at hand",
              "votes": "2",
              "replies": []
            }
          ]
        }
      ]
    },
    {
      "text": "Whats your major?",
      "votes": "2",
      "replies": [
        {
          "text": "Bachelors programme in Data Science",
          "votes": "1",
          "replies": []
        }
      ]
    },
    {
      "text": "I am going to Georgia Atlanta",
      "votes": "2",
      "replies": [
        {
          "text": "Omgggg, which uni are you going to??",
          "votes": "1",
          "replies": [
            {
              "text": "GEORGIA STATE UNIVERSITY, GOT VISA APPROVED IN MAY20",
              "votes": "2",
              "replies": []
            }
          ]
        }
      ]
    }
  ],
  "id": 243
}